codetoprompt_mcp/mcp.py
codetoprompt_mcp/mcp_tools.py
codetoprompt_mcp-0.1.0.dist-info/licenses/LICENSE
codetoprompt_mcp-0.1.0.dist-info/METADATA
codetoprompt_mcp-0.1.0.dist-info/WHEEL
codetoprompt_mcp-0.1.0.dist-info/entry_points.txt
codetoprompt_mcp-0.1.0.dist-info/top_level.txt
codetoprompt_mcp-0.1.0.dist-info/RECORD
