Metadata-Version: 2.4
Name: codetoprompt-mcp
Version: 0.1.0
Summary: An MCP server for the codetoprompt library, enabling integration with LLM agents.
Author-email: Yash Bhaskar <yash9439@gmail.com>
License: MIT
Project-URL: Homepage, https://github.com/yash9439/codetoprompt-mcp
Project-URL: Repository, https://github.com/yash9439/codetoprompt-mcp
Project-URL: Issues, https://github.com/yash9439/codetoprompt-mcp/issues
Classifier: Programming Language :: Python :: 3.10
Classifier: Programming Language :: Python :: 3.11
Classifier: Programming Language :: Python :: 3.12
Classifier: Operating System :: OS Independent
Classifier: Development Status :: 4 - Beta
Classifier: Intended Audience :: Developers
Classifier: License :: OSI Approved :: MIT License
Classifier: Topic :: Software Development :: Libraries :: Python Modules
Classifier: Topic :: Text Processing :: General
Classifier: Topic :: Utilities
Requires-Python: >=3.10
License-File: LICENSE
Requires-Dist: codetoprompt==0.6.2
Requires-Dist: mcp>=1.3.0
Provides-Extra: dev
Requires-Dist: pytest; extra == "dev"
Requires-Dist: black; extra == "dev"
Requires-Dist: isort; extra == "dev"
Requires-Dist: mypy; extra == "dev"
Dynamic: license-file
